mikud/__init__.py
mikud/_version.py
mikud/mikud.py
mikud-0.0.3.dist-info/LICENSE
mikud-0.0.3.dist-info/METADATA
mikud-0.0.3.dist-info/WHEEL
mikud-0.0.3.dist-info/top_level.txt
mikud-0.0.3.dist-info/RECORD
