Metadata-Version: 2.1
Name: mikud
Version: 0.0.3
Summary: Get mikud (zip code in israel) by address.
Home-page: https://mikud.readthedocs.io
Author: David Lev
Author-email: davidlev@telegmail.com
License: MIT
Platform: UNKNOWN
License-File: LICENSE
Requires-Dist: requests
